app_store_scraper/__init__.py
app_store_scraper/__version__.py
app_store_scraper/app_store.py
app_store_scraper/base.py
app_store_scraper/images_info.py
app_store_scraper/podcast.py
app_store_scraper_mod-0.4.0.dist-info/LICENCE
app_store_scraper_mod-0.4.0.dist-info/METADATA
app_store_scraper_mod-0.4.0.dist-info/WHEEL
app_store_scraper_mod-0.4.0.dist-info/top_level.txt
app_store_scraper_mod-0.4.0.dist-info/RECORD
