Metadata-Version: 2.1
Name: app-store-scraper-mod
Version: 0.4.0
Summary: Fork of cowboy-bebug: App Store Scraper with updated dependencies.
Home-page: https://github.com/cowboy-bebug/app-store-scraper
Author: Eric Lim
Author-email: Ashok <engineering@seiright.com>
License: MIT
Project-URL: Homepage, https://github.com/pypa/sampleproject
Project-URL: Issues, https://github.com/pypa/sampleproject/issues
Keywords: app store,ios,ios apps,podcasts,review,scraping,scraper
Classifier: Programming Language :: Python :: 3
Classifier: License :: OSI Approved :: MIT License
Classifier: Operating System :: OS Independent
Requires-Python: >=3.6
License-File: LICENCE
Requires-Dist: requests ==2.32.0
Requires-Dist: bs4 ==0.0.2
